Compress_csv_files_gcs_bucket/__init__.py
Compress_csv_files_gcs_bucket/main.py
Compress_csv_files_gcs_bucket-0.1.dist-info/METADATA
Compress_csv_files_gcs_bucket-0.1.dist-info/WHEEL
Compress_csv_files_gcs_bucket-0.1.dist-info/entry_points.txt
Compress_csv_files_gcs_bucket-0.1.dist-info/top_level.txt
Compress_csv_files_gcs_bucket-0.1.dist-info/RECORD
