Metadata-Version: 2.1
Name: Compress-csv-files-gcs-bucket
Version: 0.1
